cleanify/__init__.py
cleanify/main.py
cleanify-1.0.0.dist-info/LICENSE
cleanify-1.0.0.dist-info/METADATA
cleanify-1.0.0.dist-info/WHEEL
cleanify-1.0.0.dist-info/entry_points.txt
cleanify-1.0.0.dist-info/top_level.txt
cleanify-1.0.0.dist-info/RECORD
