Metadata-Version: 2.1
Name: cleanify
Version: 1.0.0
Summary: CLI utility to remove remove newlines, tabs from a file and copy it to your clipboard
Home-page: https://github.com/http-samc/cleanify
Author: Samarth Chitgopekar
Author-email: sam@chitgopekar.tech
License: UNKNOWN
Platform: UNKNOWN
Classifier: Topic :: Utilities
Classifier: Intended Audience :: Developers
Classifier: Environment :: Console
Classifier: Development Status :: 5 - Production/Stable
Classifier: License :: OSI Approved :: MIT License
Classifier: Operating System :: Microsoft :: Windows
Classifier: Programming Language :: Python :: 3.9
Classifier: Natural Language :: English
